MANIFEST.in
TODO.txt
bootstrap.py
buildout.cfg
setup.cfg
setup.py
docs/CHANGES.txt
docs/CREDITS.txt
docs/README.txt
src/collective/__init__.py
src/collective.googlevisualization.egg-info/PKG-INFO
src/collective.googlevisualization.egg-info/SOURCES.txt
src/collective.googlevisualization.egg-info/dependency_links.txt
src/collective.googlevisualization.egg-info/namespace_packages.txt
src/collective.googlevisualization.egg-info/not-zip-safe
src/collective.googlevisualization.egg-info/requires.txt
src/collective.googlevisualization.egg-info/top_level.txt
src/collective/googlevisualization/__init__.py
src/collective/googlevisualization/configure.zcml
src/collective/googlevisualization/googlevisualization.txt
src/collective/googlevisualization/portlet.pt
src/collective/googlevisualization/portlet.py
src/collective/googlevisualization/tests.py
src/collective/googlevisualization/browser/__init__.py
src/collective/googlevisualization/browser/chart.py
src/collective/googlevisualization/profiles/default/jsregistry.xml
src/collective/googlevisualization/profiles/default/metadata.xml
src/collective/googlevisualization/profiles/default/portlets.xml
src/collective/googlevisualization/resources/data.json
src/collective/googlevisualization/resources/index.html
src/collective/googlevisualization/resources/jquery.googlevisualization.js