Metadata-Version: 1.0
Name: collective.googlevisualization
Version: 0.1.2
Summary: Plone integration for Google Visualization API
Home-page: http://svn.plone.org/svn/collective/
Author: UNKNOWN
Author-email: UNKNOWN
License: GPL
Platform: UNKNOWN
Classifier: Programming Language :: Python
Classifier: Topic :: Software Development :: Libraries :: Python Modules
